{
  "posts": [
    {
      "href": "/blog/article/kontekstnaya-i-georeklama-premium-segment/",
      "description": "Как контекстная реклама и геореклама влияют на продажи в премиум-сегменте",
      "subtitle": "Рассказываем на примере проекта в нише дизайнерской мебели",
      "tags": [
        "Статьи"
      ],
      "tagCodes": [
        "article"
      ],
      "tagCodesNorm": [
        "article"
      ],
      "linkClass": "white-text",
      "isResource": true,
      "publishDate": "2026-03-31T10:17:01.000000Z",
      "media": {
        "kind": "picture",
        "image": "/_sa/img/blog/BcWgtbhrbCbVcjQOwqqD1do3OryaFhHsnx9IqPu7.webp"
      }
    }
  ]
}
